mimblewimble/__init__.py
mimblewimble/blockchain.py
mimblewimble/codecs.py
mimblewimble/consensus.py
mimblewimble/genesis.py
mimblewimble/keychain.py
mimblewimble/mnemonic.py
mimblewimble/serializer.py
mimblewimble/wallet.py
mimblewimble/static/__init__.py
mimblewimble/static/wordlist.json
mimblewimble-0.9.0.dist-info/licenses/LICENSE
mimblewimble-0.9.0.dist-info/METADATA
mimblewimble-0.9.0.dist-info/WHEEL
mimblewimble-0.9.0.dist-info/top_level.txt
mimblewimble-0.9.0.dist-info/RECORD
