Metadata-Version: 2.4
Name: mimblewimble
Version: 0.9.0
Summary: A toolset for processing Grin Mimblewimble data structures
Home-page: https://github.com/grinventions/mimblewimble-py
Author: Marek Narozniak
Author-email: marek.yggdrasil@gmail.com
License: MIT
Classifier: Programming Language :: Python :: 3
Classifier: Programming Language :: Python :: 2
Classifier: License :: OSI Approved :: MIT License
Classifier: Operating System :: OS Independent
License-File: LICENSE
Requires-Dist: base58
Requires-Dist: siphash-cffi
Requires-Dist: secp256k1-zkp-mw
Requires-Dist: bip_utils
Requires-Dist: bip32
Requires-Dist: pynacl
Requires-Dist: pyrage
Dynamic: author
Dynamic: author-email
Dynamic: classifier
Dynamic: description
Dynamic: description-content-type
Dynamic: home-page
Dynamic: license
Dynamic: license-file
Dynamic: requires-dist
Dynamic: summary
